pacupdate/__init__.py
pacupdate/main.py
pacupdate/shared.py
pacupdate/structs.py
pacupdate-0.4.dist-info/METADATA
pacupdate-0.4.dist-info/WHEEL
pacupdate-0.4.dist-info/entry_points.txt
pacupdate-0.4.dist-info/licenses/LICENSE
pacupdate-0.4.dist-info/RECORD
