Metadata-Version: 2.4
Name: pacupdate
Version: 0.4
Summary: A pacman update script
Project-URL: Homepage, https://github.com/Pu-Anlai/pacupdate
Project-URL: Issues, https://github.com/Pu-Anlai/pacupdate/issues
Author-email: Pu Anlai <inspectormustache@users.noreply.github.com>
License-Expression: MIT
License-File: LICENSE
Classifier: Operating System :: POSIX :: Linux
Classifier: Programming Language :: Python :: 3 :: Only
Classifier: Topic :: System :: Systems Administration
Requires-Python: >=3.11
